.DS_Store
poros/__init__.py
poros/version.py
poros/cf/__init__.py
poros/cf/apps.py
poros/cf/dataman.py
poros/cf/modeling.py
poros/cf/modeling_test.py
poros/poros_chars/__init__.py
poros/poros_chars/chinese_to_arabic.py
poros/poros_chars/something.py
poros/poros_cluster/__init__.py
poros/poros_cluster/clustering_model.py
poros/poros_cluster/sentence_encoder.py
poros/poros_cluster/similarity_matrix.py
poros/poros_common/__init__.py
poros/poros_common/checks.py
poros/poros_common/file_utils.py
poros/poros_common/from_params.py
poros/poros_common/lazy.py
poros/poros_common/meta.py
poros/poros_common/params.py
poros/poros_common/registrable.py
poros/poros_common/sequences.py
poros/poros_common/task_card.py
poros/poros_compression/__init__.py
poros/poros_compression/about_compression.py
poros/poros_dataset/__init__.py
poros/poros_layers/__init__.py
poros/poros_layers/biaffine.py
poros/poros_layers/mmoe.py
poros/poros_loss/__init__.py
poros/poros_loss/about_loss.py
poros/poros_loss/about_loss_test.py
poros/poros_metrics/__init__.py
poros/poros_train/__init__.py
poros/poros_train/about_train.py
poros-0.0.73.dist-info/LICENSE
poros-0.0.73.dist-info/METADATA
poros-0.0.73.dist-info/WHEEL
poros-0.0.73.dist-info/top_level.txt
poros-0.0.73.dist-info/RECORD
