Metadata-Version: 2.1
Name: poros
Version: 0.0.73
Summary: some useful code
Home-page: https://github.com/diqiuzhuanzhuan/poros
Author: Feynman
Author-email: diqiuzhuanzhuan@gmail.com
License: UNKNOWN
Platform: UNKNOWN
Classifier: Programming Language :: Python :: 3
Classifier: License :: OSI Approved :: MIT License
Classifier: Operating System :: OS Independent
License-File: LICENSE
Requires-Dist: pytorch-lightning
Requires-Dist: transformers (>=4.13.0)
